paper_qa_nemotron-2026.1.5.dist-info/licenses/LICENSE
paperqa_nemotron/__init__.py
paperqa_nemotron/api.py
paperqa_nemotron/py.typed
paperqa_nemotron/reader.py
paperqa_nemotron/version.py
paper_qa_nemotron-2026.1.5.dist-info/METADATA
paper_qa_nemotron-2026.1.5.dist-info/WHEEL
paper_qa_nemotron-2026.1.5.dist-info/top_level.txt
paper_qa_nemotron-2026.1.5.dist-info/RECORD
