Metadata-Version: 2.4
Name: paper-qa-nemotron
Version: 2026.1.5
Summary: PaperQA reader implemented using Nvidia's nemotron-parse VLM API
Author-email: FutureHouse technical staff <hello@futurehouse.org>
Maintainer-email: James Braza <jamesbraza@gmail.com>, Michael Skarlinski <michael.skarlinski@gmail.com>, Andrew White <white.d.andrew@gmail.com>
License:                                  Apache License
Classifier: Intended Audience :: Developers
Classifier: License :: OSI Approved :: Apache Software License
Classifier: Operating System :: OS Independent
Classifier: Programming Language :: Python :: 3 :: Only
Classifier: Programming Language :: Python :: 3.11
Classifier: Programming Language :: Python :: 3.12
Classifier: Programming Language :: Python :: 3.13
Classifier: Programming Language :: Python
Classifier: Topic :: Scientific/Engineering :: Artificial Intelligence
Requires-Python: >=3.11
License-File: LICENSE
Requires-Dist: Pillow
Requires-Dist: fhaviary[image]
Requires-Dist: fhlmi>=0.27.0
Requires-Dist: litellm>=1.71.0
Requires-Dist: numpy
Requires-Dist: paper-qa
Requires-Dist: pypdfium2>=4.22.0
Requires-Dist: tenacity
Provides-Extra: dev
Requires-Dist: docling>=2.56; extra == "dev"
Requires-Dist: fhlmi>=0.39; extra == "dev"
Requires-Dist: httpx-aiohttp; extra == "dev"
Requires-Dist: paper-qa-nemotron[sagemaker,typing]; extra == "dev"
Requires-Dist: paper-qa>=5.23; extra == "dev"
Requires-Dist: pytest-asyncio; extra == "dev"
Requires-Dist: pytest-recording; extra == "dev"
Requires-Dist: pytest-rerunfailures; extra == "dev"
Requires-Dist: pytest>=9; extra == "dev"
Requires-Dist: vcrpy>=8; extra == "dev"
Provides-Extra: sagemaker
Requires-Dist: aiobotocore; extra == "sagemaker"
Provides-Extra: typing
Requires-Dist: limits; extra == "typing"
Requires-Dist: numpy; extra == "typing"
Requires-Dist: types-Pillow; extra == "typing"
Requires-Dist: types-aiobotocore; extra == "typing"
Dynamic: license-file
